pav/__init__.py
pav/cli.py
pav/mapping
pav/req.py
pav/utils.py
pav-1.4.2.dist-info/licenses/LICENSE
pav-1.4.2.dist-info/METADATA
pav-1.4.2.dist-info/WHEEL
pav-1.4.2.dist-info/entry_points.txt
pav-1.4.2.dist-info/top_level.txt
pav-1.4.2.dist-info/RECORD
