Metadata-Version: 2.4
Name: pav
Version: 1.4.2
Summary: PAV is a Python library with features to easily work with venv
Author-email: Arian <ariannasiri86@gmail.com>
License-Expression: MIT
Project-URL: Homepage, https://github.com/ArianN8610/PAV
Requires-Python: >=3.6
License-File: LICENSE
Requires-Dist: click==8.1.8
Dynamic: license-file
